machinery/__init__.py
mw_machinery-0.0.1.dist-info/WHEEL
mw_machinery-0.0.1.dist-info/METADATA
mw_machinery-0.0.1.dist-info/RECORD
