Metadata-Version: 2.1
Name: mw-machinery
Version: 0.0.1
Summary: This is the machine description framework
Home-page: https://projects.om-office.de/frans/machinery.git
Author: Frans Fürst
Author-email: frans.fuerst+gitlab@protonmail.com
Requires-Python: >=3.8,<3.11
Classifier: Programming Language :: Python :: 3
Classifier: Programming Language :: Python :: 3.8
Classifier: Programming Language :: Python :: 3.9
Classifier: Programming Language :: Python :: 3.10
Requires-Dist: pygame (>=2.1.2,<3.0.0)
Project-URL: Repository, https://projects.om-office.de/frans/machinery.git
